scopecuisine/__init__.py
scopecuisine/gui.py
scopecuisine/multiprocessing.py
scopecuisine/rolling_buffer.py
scopecuisine/notifiers/__init__.py
scopecuisine/notifiers/interface.py
scopecuisine/notifiers/yagmail.py
scopecuisine/theknights/__init__.py
scopecuisine/theknights/constants.py
scopecuisine/theknights/error_codes.py
scopecuisine/theknights/errors.py
scopecuisine/theknights/stream_readers.py
scopecuisine/theknights/stream_writers.py
scopecuisine/theknights/task.py
scopecuisine/theknights/theknights.py
scopecuisine/theknights/_task_modules/__init__.py
scopecuisine/theknights/_task_modules/ai_channel_collection.py
scopecuisine/theknights/_task_modules/ao_channel_collection.py
scopecuisine/theknights/_task_modules/ci_channel_collection.py
scopecuisine/theknights/_task_modules/co_channel_collection.py
scopecuisine/theknights/_task_modules/di_channel_collection.py
scopecuisine/theknights/_task_modules/do_channel_collection.py
scopecuisine/theknights/_task_modules/export_signals.py
scopecuisine/theknights/_task_modules/in_stream.py
scopecuisine/theknights/_task_modules/out_stream.py
scopecuisine/theknights/_task_modules/timing.py
scopecuisine/theknights/_task_modules/triggers.py
scopecuisine/theknights/_task_modules/triggering/__init__.py
scopecuisine/theknights/_task_modules/triggering/start_trigger.py
scopecuisine-0.1.3.dist-info/AUTHORS.rst
scopecuisine-0.1.3.dist-info/LICENSE
scopecuisine-0.1.3.dist-info/METADATA
scopecuisine-0.1.3.dist-info/WHEEL
scopecuisine-0.1.3.dist-info/top_level.txt
scopecuisine-0.1.3.dist-info/RECORD
