Metadata-Version: 2.1
Name: scopecuisine
Version: 0.1.3
Summary: Python utilities for microscope control software
Home-page: https://github.com/portugueslab/scopecuisine
Author: portugueslab
Author-email: vilim@neuro.mpg.de
License: GNU General Public License v3
Keywords: scopecuisine
Platform: UNKNOWN
Classifier: Development Status :: 2 - Pre-Alpha
Classifier: Intended Audience :: Developers
Classifier: License :: OSI Approved :: GNU General Public License v3 (GPLv3)
Classifier: Natural Language :: English
Classifier: Programming Language :: Python :: 3
Classifier: Programming Language :: Python :: 3.5
Classifier: Programming Language :: Python :: 3.6
Classifier: Programming Language :: Python :: 3.7
Classifier: Programming Language :: Python :: 3.8
Requires-Python: >=3.5
Requires-Dist: yagmail
Requires-Dist: numpy
Requires-Dist: numba
